docs/conf.py
pastastore/__init__.py
pastastore/base.py
pastastore/connectors.py
pastastore/datasets.py
pastastore/plotting.py
pastastore/store.py
pastastore/styling.py
pastastore/typing.py
pastastore/util.py
pastastore/validator.py
pastastore/version.py
pastastore/yaml_interface.py
pastastore/extensions/__init__.py
pastastore/extensions/accessor.py
pastastore/extensions/hpd.py
pastastore-1.11.0.dist-info/licenses/LICENSE
tests/conftest.py
tests/test_001_import.py
tests/test_002_connectors.py
tests/test_003_pastastore.py
tests/test_004_yaml.py
tests/test_005_maps_plots.py
tests/test_006_benchmark.py
tests/test_007_hpdextension.py
tests/test_008_stressmodels.py
pastastore-1.11.0.dist-info/METADATA
pastastore-1.11.0.dist-info/WHEEL
pastastore-1.11.0.dist-info/top_level.txt
pastastore-1.11.0.dist-info/RECORD
