Metadata-Version: 2.4
Name: pastastore
Version: 1.11.0
Summary: Tools for managing Pastas time series models.
Author: D.A. Brakenhoff
Maintainer-email: "D.A. Brakenhoff" <d.brakenhoff@artesia-water.nl>, "R. Calje" <r.calje@artesia-water.nl>, "M.A. Vonk" <m.vonk@artesia-water.nl>
License: The MIT License (MIT)
Project-URL: homepage, https://github.com/pastas/pastastore
Project-URL: repository, https://github.com/pastas/pastastore
Project-URL: documentation, https://pastastore.readthedocs.io/en/latest/
Keywords: hydrology,groundwater,time series,analysis,database
Classifier: Development Status :: 4 - Beta
Classifier: Intended Audience :: Science/Research
Classifier: Intended Audience :: Other Audience
Classifier: License :: OSI Approved :: MIT License
Classifier: Operating System :: Microsoft :: Windows
Classifier: Operating System :: POSIX
Classifier: Operating System :: Unix
Classifier: Operating System :: MacOS
Classifier: Programming Language :: Python
Classifier: Programming Language :: Python :: 3
Classifier: Programming Language :: Python :: 3.10
Classifier: Programming Language :: Python :: 3.11
Classifier: Programming Language :: Python :: 3.12
Classifier: Programming Language :: Python :: 3.13
Classifier: Programming Language :: Python :: 3 :: Only
Classifier: Topic :: Scientific/Engineering :: Hydrology
Requires-Python: >=3.10
License-File: LICENSE
Requires-Dist: pastas>=0.13
Requires-Dist: tqdm>=4.36
Requires-Dist: pyyaml
Requires-Dist: colorama
Provides-Extra: full
Requires-Dist: pastastore[arcticdb,optional]; extra == "full"
Requires-Dist: hydropandas; extra == "full"
Provides-Extra: extensions
Requires-Dist: hydropandas; extra == "extensions"
Provides-Extra: optional
Requires-Dist: contextily; extra == "optional"
Requires-Dist: pyproj; extra == "optional"
Requires-Dist: adjustText; extra == "optional"
Provides-Extra: arcticdb
Requires-Dist: arcticdb; extra == "arcticdb"
Provides-Extra: lint
Requires-Dist: ruff; extra == "lint"
Provides-Extra: pytest
Requires-Dist: coverage; extra == "pytest"
Requires-Dist: codecov; extra == "pytest"
Requires-Dist: pytest; extra == "pytest"
Requires-Dist: pytest-cov; extra == "pytest"
Requires-Dist: pytest-dependency; extra == "pytest"
Requires-Dist: pytest-benchmark; extra == "pytest"
Requires-Dist: codacy-coverage; extra == "pytest"
Provides-Extra: docs
Requires-Dist: pastastore[optional]; extra == "docs"
Requires-Dist: sphinx_rtd_theme; extra == "docs"
Requires-Dist: Ipython; extra == "docs"
Requires-Dist: ipykernel; extra == "docs"
Requires-Dist: nbsphinx; extra == "docs"
Requires-Dist: nbsphinx_link; extra == "docs"
Provides-Extra: test
Requires-Dist: pastastore[arcticdb,optional,pytest]; extra == "test"
Requires-Dist: hydropandas[full]; extra == "test"
Provides-Extra: dev
Requires-Dist: pastastore[docs,lint,test]; extra == "dev"
Dynamic: license-file
